koding/__init__.py
koding/example.py
koding-0.0.1.dist-info/LICENCE
koding-0.0.1.dist-info/METADATA
koding-0.0.1.dist-info/WHEEL
koding-0.0.1.dist-info/top_level.txt
koding-0.0.1.dist-info/RECORD
